panopticml/__init__.py
panopticml/compute_vector_task.py
panopticml/panoptic_ml.py
panopticml/utils.py
panopticml/compute/__init__.py
panopticml/compute/clustering.py
panopticml/compute/faiss_tree.py
panopticml/compute/transformer.py
panopticml/compute/transformers/__init__.py
panopticml-0.0.5.dist-info/METADATA
panopticml-0.0.5.dist-info/WHEEL
panopticml-0.0.5.dist-info/RECORD
