Metadata-Version: 2.4
Name: panopticml
Version: 0.0.5
Summary: A package for Panoptic ML
Project-URL: Homepage, https://github.com/CERES-Sorbonne/PanopticML
Project-URL: Bug Tracker, https://github.com/CERES-Sorbonne/PanopticML/issues
Author-email: Félix Alié <felix.alie@sorbonne-universite.fr>
Classifier: Development Status :: 4 - Beta
Classifier: Intended Audience :: Science/Research
Classifier: License :: OSI Approved :: Mozilla Public License 2.0 (MPL 2.0)
Classifier: Operating System :: OS Independent
Classifier: Programming Language :: Python
Classifier: Programming Language :: Python :: 3
Classifier: Programming Language :: Python :: 3.10
Classifier: Programming Language :: Python :: 3.11
Classifier: Programming Language :: Python :: 3.12
Classifier: Programming Language :: Python :: Implementation :: CPython
Classifier: Programming Language :: Python :: Implementation :: PyPy
Requires-Python: >=3.10
Requires-Dist: faiss-cpu<1.11.0
Requires-Dist: mistralai
Requires-Dist: numpy
Requires-Dist: scikit-learn
Requires-Dist: scipy
Requires-Dist: torch
Requires-Dist: torchvision
Requires-Dist: transformers<4.52.0
